fusion/__init__.py
fusion/change_aggregator.py
fusion/extensions_loader.py
fusion/fsm.py
fusion/logging.py
fusion/loop.py
fusion/view.py
fusion/libs/channel.py
fusion/libs/command.py
fusion/libs/state.py
fusion/libs/action/__init__.py
fusion/libs/action/action_call.py
fusion/libs/entity/__init__.py
fusion/libs/entity/change.py
fusion/platform/qt_widgets/__init__.py
fusion/platform/qt_widgets/qt_main_loop.py
fusion/storage/in_memory_repository.py
fusion/storage/repository.py
fusion/util/__init__.py
fusion/util/color.py
fusion/util/point2d.py
fusion/util/rectangle.py
fusion/visual_inspection/action_camera.py
python_fusion-0.7.5.dist-info/LICENSE
python_fusion-0.7.5.dist-info/METADATA
python_fusion-0.7.5.dist-info/WHEEL
python_fusion-0.7.5.dist-info/top_level.txt
python_fusion-0.7.5.dist-info/RECORD
