Metadata-Version: 2.1
Name: python-fusion
Version: 0.7.5
Summary: An experimental state manager
Author-email: Petko Dichev <pditchev@gmail.com>
License: GPLv3
Classifier: Development Status :: 3 - Alpha
Classifier: Programming Language :: Python :: 3
Classifier: License :: OSI Approved :: GNU General Public License v3 (GPLv3)
Classifier: Operating System :: OS Independent
Requires-Python: >=3.10
License-File: LICENSE
